brainiac/__init__.py
brainiac/configuration_brainiac.py
brainiac/modeling_brainiac.py
brainiac_model-0.1.1.dist-info/LICENSE
brainiac_model-0.1.1.dist-info/METADATA
brainiac_model-0.1.1.dist-info/WHEEL
brainiac_model-0.1.1.dist-info/top_level.txt
brainiac_model-0.1.1.dist-info/RECORD
