Metadata-Version: 2.1
Name: brainiac-model
Version: 0.1.1
Summary: A 3D ResNet50 model for brain MRI analysis
Home-page: https://huggingface.co/Divytak/brainiac
Author: Divyanshu
Classifier: Programming Language :: Python :: 3
Classifier: License :: OSI Approved :: MIT License
Classifier: Operating System :: OS Independent
Requires-Python: >=3.6
License-File: LICENSE
Requires-Dist: torch>=1.9.0
Requires-Dist: transformers>=4.20.0
Requires-Dist: monai>=1.0.0
